tgcrypto.cpython-310-x86_64-linux-gnu.so
tests/__init__.py
tests/cbc/test_cbc.py
tests/cbc/__init__.py
tests/ige/test_ige.py
tests/ige/__init__.py
tests/ctr/test_ctr.py
tests/ctr/__init__.py
tgcrypto_devilaiger-1.2.6.dist-info/WHEEL
tgcrypto_devilaiger-1.2.6.dist-info/top_level.txt
tgcrypto_devilaiger-1.2.6.dist-info/METADATA
tgcrypto_devilaiger-1.2.6.dist-info/RECORD
