Metadata-Version: 2.1
Name: tgcrypto-devilaiger
Version: 1.2.6
Summary: Fast and Portable Cryptography Extension Library for Pyrogram
Home-page: https://github.com/pyrogram
Download-URL: https://github.com/pyrogram/tgcrypto/releases/latest
Author: Dan
Author-email: Dan <dan@pyrogram.org>
License: LGPL-3.0-or-later
Keywords: crypto,telegram,pyrogram,tgcrypto
Classifier: License :: OSI Approved :: GNU Lesser General Public License v3 (LGPLv3)
Classifier: Programming Language :: Python
Classifier: Programming Language :: Python :: 3
Classifier: Programming Language :: Python :: 3 :: Only
Classifier: Programming Language :: Python :: 3.7
Classifier: Programming Language :: Python :: 3.8
Classifier: Programming Language :: Python :: 3.9
Classifier: Programming Language :: Python :: 3.10
Classifier: Programming Language :: Python :: 3.11
Classifier: Programming Language :: Python :: 3.12
Classifier: Programming Language :: Python :: 3.13
Classifier: Operating System :: OS Independent
Requires-Python: ~=3.7
